README.rst
setup.py
ubitstring.py
micropython_bitstring.egg-info/PKG-INFO
micropython_bitstring.egg-info/SOURCES.txt
micropython_bitstring.egg-info/dependency_links.txt
micropython_bitstring.egg-info/requires.txt
micropython_bitstring.egg-info/top_level.txt
test/test_bits.py
test/test_bitstore.py