Metadata-Version: 1.1
Name: micropython-bitstring
Version: 0.1.0
Summary: Very stripped down version of Scrott Griffith's Bitstring package.
Home-page: https://github.com/mjuenema/micropython-bitstring
Author: Markus Juenemann
Author-email: markus@juenemann.net
License: The MIT License: http://www.opensource.org/licenses/mit-license.php
Download-URL: https://pypi.python.org/pypi/micropython-bitstring/
Platform: all
Classifier: Development Status :: 4 - Beta
Classifier: Intended Audience :: Developers
Classifier: Operating System :: OS Independent
Classifier: License :: OSI Approved :: MIT License
Classifier: Programming Language :: Python :: 3
Classifier: Programming Language :: Python :: Implementation :: MicroPython
Classifier: Topic :: Software Development :: Libraries :: Python Modules
